_kastore.cpython-39-darwin.so
kastore/__init__.py
kastore/__main__.py
kastore/_version.py
kastore/cli.py
kastore/exceptions.py
kastore/store.py
kastore/include/kastore.h
kastore-0.3.3.dist-info/LICENSE
kastore-0.3.3.dist-info/METADATA
kastore-0.3.3.dist-info/WHEEL
kastore-0.3.3.dist-info/entry_points.txt
kastore-0.3.3.dist-info/top_level.txt
kastore-0.3.3.dist-info/RECORD
